poldantic/__init__.py
poldantic/exceptions.py
poldantic/infer_polars.py
poldantic/infer_pydantic.py
poldantic/py.typed
poldantic-0.3.1.dist-info/LICENSE
poldantic-0.3.1.dist-info/METADATA
poldantic-0.3.1.dist-info/WHEEL
poldantic-0.3.1.dist-info/top_level.txt
poldantic-0.3.1.dist-info/RECORD
