Metadata-Version: 2.1
Name: poldantic
Version: 0.3.1
Summary: Convert Pydantic models to Polars schemas
Author-email: Odos Matthews <odosmatthews@gmail.com>
Project-URL: Repository, https://github.com/eddiethedean/poldantic
Project-URL: Homepage, https://github.com/eddiethedean/poldantic
Project-URL: Issues, https://github.com/eddiethedean/poldantic/issues
Requires-Python: >=3.8
License-File: LICENSE
Requires-Dist: pydantic>=2.0
Requires-Dist: polars>=0.20.0
Requires-Dist: typing-extensions>=4.0.0; python_version < "3.9"
Provides-Extra: dev
Requires-Dist: pytest>=7.0; extra == "dev"
Requires-Dist: pytest-cov>=4.0; extra == "dev"
Requires-Dist: pytest-xdist>=3.0; extra == "dev"
Requires-Dist: pytest-timeout>=2.0; extra == "dev"
Requires-Dist: pytest-benchmark>=4.0; extra == "dev"
Requires-Dist: ruff>=0.1.0; extra == "dev"
Requires-Dist: mypy>=1.0; extra == "dev"
Requires-Dist: pre-commit>=3.0; extra == "dev"
Provides-Extra: test
Requires-Dist: pytest>=7.0; extra == "test"
Requires-Dist: email-validator>=2.0; extra == "test"
